{
	"id": "776f3822-9315-484a-a20e-13ee2daa30c2",
	"name": "Stargate",
	"values": [
		{
			"key": "databaseid",
			"value": "1b0834a4-d9bc-43c4-a2b0-ae9a46e40203",
			"enabled": false
		},
		{
			"key": "region",
			"value": "us-east1",
			"enabled": true
		},
		{
			"key": "unique-UUID",
			"value": "gmc-test",
			"enabled": false
		},
		{
			"key": "username",
			"value": "james",
			"enabled": true
		},
		{
			"key": "password",
			"value": "SuperSecret",
			"enabled": true
		},
		{
			"key": "keyspace",
			"value": "document",
			"enabled": true
		},
		{
			"key": "authToken",
			"value": "",
			"enabled": false
		},
		{
			"key": "db",
			"value": "26cc1a45-b980-4df4-ae2c-27c195bc1cb8",
			"enabled": true
		},
		{
			"key": "token",
			"value": "c2dbaa25-23a0-4313-a4cf-047944997873",
			"enabled": true
		},
		{
			"key": "collection",
			"value": "people",
			"enabled": true
		},
		{
			"key": "documentId",
			"value": "e2d22267-c09e-460f-b04b-5b118b5b5d63",
			"enabled": false
		}
	],
	"_postman_variable_scope": "environment",
	"_postman_exported_at": "2020-11-19T21:04:53.240Z",
	"_postman_exported_using": "Postman/7.35.0"
}